hadron_server_weather/ __main__.py
hadron_server_weather/__init__.py
hadron_server_weather/server.py
hadron_server_weather-0.1.0.dist-info/METADATA
hadron_server_weather-0.1.0.dist-info/WHEEL
hadron_server_weather-0.1.0.dist-info/entry_points.txt
hadron_server_weather-0.1.0.dist-info/top_level.txt
hadron_server_weather-0.1.0.dist-info/RECORD
